README.md
setup.py
CharTask/__init__.py
CharTask/_task.py
CharTask.egg-info/PKG-INFO
CharTask.egg-info/SOURCES.txt
CharTask.egg-info/dependency_links.txt
CharTask.egg-info/top_level.txt
CharTask/_dicts/__init__.py
CharTask/_dicts/tasks.json